laminated/__init__.py
laminated/laminated.py
laminated-0.1.dist-info/DESCRIPTION.rst
laminated-0.1.dist-info/METADATA
laminated-0.1.dist-info/RECORD
laminated-0.1.dist-info/WHEEL
laminated-0.1.dist-info/metadata.json
laminated-0.1.dist-info/top_level.txt
