Metadata-Version: 2.0
Name: laminated
Version: 0.1
Summary: Dictionary like object with layers support
Home-page: https://github.com/EvgeniyMakhmudov/laminated
Author: Makhmudov Evgeniy
Author-email: john_16@list.ru
License: MIT
Keywords: dict dictionary layers
Platform: UNKNOWN
Classifier: Development Status :: 4 - Beta
Classifier: Intended Audience :: Developers
Classifier: License :: OSI Approved :: MIT License
Classifier: Operating System :: OS Independent
Classifier: Programming Language :: Python
Classifier: Topic :: Software Development :: Libraries
